odoo/addons/sale_coupon_domain_product_discount/README.rst
odoo/addons/sale_coupon_domain_product_discount/__init__.py
odoo/addons/sale_coupon_domain_product_discount/__manifest__.py
odoo/addons/sale_coupon_domain_product_discount/i18n/es.po
odoo/addons/sale_coupon_domain_product_discount/i18n/sale_coupon_domain_product_discount.pot
odoo/addons/sale_coupon_domain_product_discount/models/__init__.py
odoo/addons/sale_coupon_domain_product_discount/models/coupon_program.py
odoo/addons/sale_coupon_domain_product_discount/models/sale_order.py
odoo/addons/sale_coupon_domain_product_discount/readme/CONTRIBUTORS.rst
odoo/addons/sale_coupon_domain_product_discount/readme/DESCRIPTION.rst
odoo/addons/sale_coupon_domain_product_discount/readme/USAGE.rst
odoo/addons/sale_coupon_domain_product_discount/static/description/icon.png
odoo/addons/sale_coupon_domain_product_discount/static/description/index.html
odoo/addons/sale_coupon_domain_product_discount/tests/__init__.py
odoo/addons/sale_coupon_domain_product_discount/tests/test_domain_product_discount.py
odoo_addon_sale_coupon_domain_product_discount-15.0.1.0.1.2.dist-info/METADATA
odoo_addon_sale_coupon_domain_product_discount-15.0.1.0.1.2.dist-info/WHEEL
odoo_addon_sale_coupon_domain_product_discount-15.0.1.0.1.2.dist-info/top_level.txt
odoo_addon_sale_coupon_domain_product_discount-15.0.1.0.1.2.dist-info/RECORD
